{
  "headers": {
    "alt-svc": "h3=\":443\"; ma=86400, h3-29=\":443\"; ma=86400",
    "date": "Mon, 08 May 2023 03:40:05 GMT",
    "vary": "Origin, Accept-Encoding",
    "x-content-source": "r2",
    "access-control-allow-methods": "*",
    "content-length": "3722",
    "cache-control": "public, max-age=31536000, immutable",
    "access-control-allow-origin": "*",
    "report-to": "{\"endpoints\":[{\"url\":\"https:\\/\\/a.nel.cloudflare.com\\/report\\/v3?s=mjz9RgAbO2t3rMsR5iqKhZTX414jWTMRP1%2B5etqE0eLPfK3ZX2dWX6dwv%2F2t12Bj7%2Bf47NKhglTLz38KF7Uv2xCJMV%2BtOiXiBeNKsW1q9kJxh12SfthiP2I%3D\"}],\"group\":\"cf-nel\",\"max_age\":604800}",
    "nel": "{\"success_fraction\":0,\"report_to\":\"cf-nel\",\"max_age\":604800}",
    "server": "cloudflare",
    "cf-ray": "7c3eaddf6ae60ca8-EWR",
    "content-type": "application/typescript; charset=utf-8"
  },
  "url": "https://esm.sh/v119/yjs@13.5.42/dist/src/utils/Transaction.d.ts",
  "now": {
    "secs_since_epoch": 1683517285,
    "nanos_since_epoch": 4991547
  }
}