{
  "headers": {
    "nel": "{\"success_fraction\":0,\"report_to\":\"cf-nel\",\"max_age\":604800}",
    "cf-ray": "7c3ead251d36443e-EWR",
    "cf-cache-status": "HIT",
    "alt-svc": "h3=\":443\"; ma=86400, h3-29=\":443\"; ma=86400",
    "age": "713",
    "date": "Mon, 08 May 2023 03:39:34 GMT",
    "vary": "Origin, User-Agent, Accept-Encoding",
    "access-control-allow-methods": "*",
    "content-type": "application/javascript; charset=utf-8",
    "access-control-expose-headers": "X-TypeScript-Types",
    "access-control-allow-origin": "*",
    "report-to": "{\"endpoints\":[{\"url\":\"https:\\/\\/a.nel.cloudflare.com\\/report\\/v3?s=8cgm8%2BLu9l5JY89iNIS5QErS7qzLIbZz%2Bd500Wu%2Bp7xl3tdVbbZvFps6u47u4eNRhWIj8iRnqwcx%2B%2BF0lZCtVW5TGk7Wy1cwfbMBbNroxkHs4i8bPERVCiA%3D\"}],\"group\":\"cf-nel\",\"max_age\":604800}",
    "server": "cloudflare",
    "cache-control": "public, max-age=86400",
    "last-modified": "Mon, 08 May 2023 03:27:41 GMT",
    "x-typescript-types": "https://esm.sh/v119/@capacitor-community/sqlite@4.6.0/X-ZS9AY2FwYWNpdG9yL2NvcmU/dist/esm/index.d.ts"
  },
  "url": "https://esm.sh/@capacitor-community/sqlite@4.6.0?external=@capacitor/core",
  "now": {
    "secs_since_epoch": 1683517174,
    "nanos_since_epoch": 601280255
  }
}